node_graph/__init__.py
node_graph/diagram.py
node_graph/frontend/build/asset-manifest.json
node_graph/frontend/build/bootstrap.min.css
node_graph/frontend/build/index.html
node_graph/frontend/build/precache-manifest.55f5c93ab296dba5a3249bf7c95da0f9.js
node_graph/frontend/build/service-worker.js
node_graph/frontend/build/static/css/2.f0e4fa12.chunk.css
node_graph/frontend/build/static/css/2.f0e4fa12.chunk.css.map
node_graph/frontend/build/static/css/main.92405922.chunk.css
node_graph/frontend/build/static/css/main.92405922.chunk.css.map
node_graph/frontend/build/static/js/2.96606a7d.chunk.js
node_graph/frontend/build/static/js/2.96606a7d.chunk.js.LICENSE.txt
node_graph/frontend/build/static/js/2.96606a7d.chunk.js.map
node_graph/frontend/build/static/js/main.a17ec785.chunk.js
node_graph/frontend/build/static/js/main.a17ec785.chunk.js.map
node_graph/frontend/build/static/js/runtime-main.2cb3803c.js
node_graph/frontend/build/static/js/runtime-main.2cb3803c.js.map
streamlit_node_graph-0.1.4.dist-info/LICENSE
streamlit_node_graph-0.1.4.dist-info/METADATA
streamlit_node_graph-0.1.4.dist-info/WHEEL
streamlit_node_graph-0.1.4.dist-info/top_level.txt
streamlit_node_graph-0.1.4.dist-info/RECORD
