Metadata-Version: 2.1
Name: streamlit-node-graph
Version: 0.1.4
Home-page: 
Author: 
Author-email: 
Requires-Python: >=3.6
License-File: LICENSE
Requires-Dist: streamlit (>=0.63)
